pantronix_logging.py
pantronix_logging-0.1.1.dist-info/METADATA
pantronix_logging-0.1.1.dist-info/WHEEL
pantronix_logging-0.1.1.dist-info/entry_points.txt
pantronix_logging-0.1.1.dist-info/top_level.txt
pantronix_logging-0.1.1.dist-info/RECORD
