Metadata-Version: 2.4
Name: pantronix_logging
Version: 0.1.1
Summary: Add your description here
Requires-Python: >=3.13
Requires-Dist: rich>=14.0.0
Requires-Dist: typer>=0.16.0
